python_toon/__init__.py
python_toon/constants.py
python_toon/formatter.py
python_toon/main.py
python_toon/normaliser.py
python_toon/primitive.py
python_toon/types.py
python_toon/writer.py
json_toon_fmt-0.1.0.dist-info/METADATA
json_toon_fmt-0.1.0.dist-info/WHEEL
json_toon_fmt-0.1.0.dist-info/top_level.txt
json_toon_fmt-0.1.0.dist-info/RECORD
