Metadata-Version: 2.4
Name: json-toon-fmt
Version: 0.1.0
Summary: JSON to TOON converter
Author: Naman Gupta
License: MIT License
Project-URL: Homepage, https://github.com/Namangupta123/python-toon
Project-URL: LinkedIn, https://www.linkedin.com/in/naman-gupta-cse
Keywords: python,formatter,normaliser,ast
Classifier: Programming Language :: Python :: 3
Classifier: License :: OSI Approved :: MIT License
Classifier: Operating System :: OS Independent
Requires-Python: >=3.8
